target_postgres/__init__.py
target_postgres/db_sync.py
pipelinewise_target_postgres-2.1.2.dist-info/LICENSE
pipelinewise_target_postgres-2.1.2.dist-info/METADATA
pipelinewise_target_postgres-2.1.2.dist-info/WHEEL
pipelinewise_target_postgres-2.1.2.dist-info/entry_points.txt
pipelinewise_target_postgres-2.1.2.dist-info/top_level.txt
pipelinewise_target_postgres-2.1.2.dist-info/RECORD
