Metadata-Version: 2.1
Name: pipelinewise-target-postgres
Version: 2.1.2
Summary: Singer.io target for loading data to PostgreSQL - PipelineWise compatible
Home-page: https://github.com/transferwise/pipelinewise-target-postgres
Author: TransferWise
Classifier: License :: OSI Approved :: Apache Software License
Classifier: Programming Language :: Python :: 3 :: Only
License-File: LICENSE
Requires-Dist: pipelinewise-singer-python (==1.*)
Requires-Dist: psycopg2-binary (==2.9.5)
Requires-Dist: inflection (==0.3.1)
Requires-Dist: joblib (==1.2.0)
Provides-Extra: test
Requires-Dist: pytest (==6.2.5) ; extra == 'test'
Requires-Dist: pylint (==2.6.0) ; extra == 'test'
Requires-Dist: pytest-cov (==2.10.1) ; extra == 'test'
